{
    "basic-member-page": {
        "id": 54,
        "name": "basic-member-page",
        "fieldgroups_id": "basic-member-page",
        "flags": 0,
        "cache_time": 0,
        "useRoles": 0,
        "noInherit": 0,
        "childrenTemplatesID": 0,
        "sortfield": "",
        "noChildren": "",
        "noParents": "",
        "childTemplates": [],
        "parentTemplates": [],
        "allowPageNum": 0,
        "allowChangeUser": 0,
        "redirectLogin": 0,
        "urlSegments": 0,
        "https": 0,
        "slashUrls": 1,
        "slashPageNum": 0,
        "slashUrlSegments": 0,
        "altFilename": "",
        "guestSearchable": 0,
        "pageClass": "",
        "childNameFormat": "",
        "pageLabelField": "fa-user title",
        "noGlobal": 0,
        "noMove": 0,
        "noTrash": 0,
        "noSettings": 0,
        "noChangeTemplate": 0,
        "noShortcut": 0,
        "noUnpublish": 0,
        "noLang": 0,
        "compile": 0,
        "nameContentTab": 0,
        "noCacheGetVars": "",
        "noCachePostVars": "",
        "useCacheForUsers": 0,
        "cacheExpire": 0,
        "cacheExpirePages": [],
        "cacheExpireSelector": "",
        "label": "",
        "tags": "",
        "titleNames": 0,
        "noPrependTemplateFile": 0,
        "noAppendTemplateFile": 0,
        "prependFile": "",
        "appendFile": "",
        "pagefileSecure": 0,
        "tabContent": "",
        "tabChildren": "",
        "nameLabel": "",
        "contentType": "",
        "errorAction": 0,
        "connectedFieldID": null,
        "ns": "ProcessWire",
        "fieldgroupFields": [
            "title"
        ],
        "fieldgroupContexts": {
            "title": []
        }
    },
    "basic-page": {
        "id": 29,
        "name": "basic-page",
        "fieldgroups_id": "basic-page",
        "flags": 0,
        "cache_time": 0,
        "useRoles": 1,
        "editRoles": [
            "editor",
            "member",
            "admin"
        ],
        "addRoles": [
            "editor",
            "member",
            "admin"
        ],
        "createRoles": [
            "member",
            "admin"
        ],
        "rolesPermissions": [],
        "noInherit": 0,
        "childrenTemplatesID": 0,
        "sortfield": "",
        "noChildren": "",
        "noParents": "",
        "childTemplates": [],
        "parentTemplates": [],
        "allowPageNum": 0,
        "allowChangeUser": 0,
        "redirectLogin": 0,
        "urlSegments": 0,
        "https": 0,
        "slashUrls": 1,
        "slashPageNum": 0,
        "slashUrlSegments": 0,
        "altFilename": "",
        "guestSearchable": 0,
        "pageClass": "",
        "childNameFormat": "",
        "pageLabelField": "fa-file-text-o title",
        "noGlobal": 0,
        "noMove": 0,
        "noTrash": 0,
        "noSettings": 0,
        "noChangeTemplate": 0,
        "noShortcut": 0,
        "noUnpublish": 0,
        "noLang": 0,
        "compile": 0,
        "nameContentTab": 0,
        "noCacheGetVars": "",
        "noCachePostVars": "",
        "useCacheForUsers": 0,
        "cacheExpire": 0,
        "cacheExpirePages": [],
        "cacheExpireSelector": "",
        "label": "Basic Page",
        "tags": "",
        "titleNames": 0,
        "noPrependTemplateFile": 0,
        "noAppendTemplateFile": 0,
        "prependFile": "",
        "appendFile": "",
        "pagefileSecure": 0,
        "tabContent": "",
        "tabChildren": "",
        "nameLabel": "",
        "contentType": "",
        "errorAction": 0,
        "connectedFieldID": null,
        "ns": "ProcessWire",
        "label1021": "Basic Page",
        "roles": [
            "guest",
            "editor",
            "member",
            "admin"
        ],
        "fieldgroupFields": [
            "title",
            "content",
            "images"
        ],
        "fieldgroupContexts": {
            "title": [],
            "content": [],
            "images": []
        }
    },
    "event": {
        "id": 48,
        "name": "event",
        "fieldgroups_id": "event",
        "flags": 0,
        "cache_time": 0,
        "useRoles": 0,
        "noInherit": 0,
        "childrenTemplatesID": 0,
        "sortfield": "",
        "noChildren": "",
        "noParents": "",
        "childTemplates": [],
        "parentTemplates": [],
        "allowPageNum": 0,
        "allowChangeUser": 0,
        "redirectLogin": 0,
        "urlSegments": 0,
        "https": 0,
        "slashUrls": 1,
        "slashPageNum": 0,
        "slashUrlSegments": 0,
        "altFilename": "",
        "guestSearchable": 0,
        "pageClass": "",
        "childNameFormat": "",
        "pageLabelField": "fa-calendar title",
        "noGlobal": 0,
        "noMove": 0,
        "noTrash": 0,
        "noSettings": 0,
        "noChangeTemplate": 0,
        "noShortcut": 0,
        "noUnpublish": 0,
        "noLang": 0,
        "compile": 0,
        "nameContentTab": 0,
        "noCacheGetVars": "",
        "noCachePostVars": "",
        "useCacheForUsers": 0,
        "cacheExpire": 0,
        "cacheExpirePages": [],
        "cacheExpireSelector": "",
        "label": "Event",
        "tags": "",
        "titleNames": 0,
        "noPrependTemplateFile": 0,
        "noAppendTemplateFile": 0,
        "prependFile": "",
        "appendFile": "",
        "pagefileSecure": 0,
        "tabContent": "",
        "tabChildren": "",
        "nameLabel": "",
        "contentType": "",
        "errorAction": 0,
        "connectedFieldID": null,
        "ns": "ProcessWire",
        "label1021": "Event",
        "fieldgroupFields": [
            "speaker_name",
            "title",
            "event_date",
            "event_end_date",
            "event_location",
            "event_abstract",
            "content",
            "images",
            "project_reference",
            "user_reference"
        ],
        "fieldgroupContexts": {
            "speaker_name": {
                "columnWidth": 50,
                "maxlength": 2048
            },
            "title": {
                "columnWidth": 50
            },
            "event_date": {
                "columnWidth": 50
            },
            "event_end_date": {
                "columnWidth": 50
            },
            "event_location": [],
            "event_abstract": [],
            "content": [],
            "images": [],
            "project_reference": {
                "columnWidth": 50
            },
            "user_reference": {
                "columnWidth": 50
            }
        }
    },
    "events-overview": {
        "id": 47,
        "name": "events-overview",
        "fieldgroups_id": "events-overview",
        "flags": 0,
        "cache_time": 0,
        "useRoles": 0,
        "noInherit": 0,
        "childrenTemplatesID": 0,
        "sortfield": "",
        "noChildren": "",
        "noParents": "",
        "childTemplates": [
            "event"
        ],
        "parentTemplates": [],
        "allowPageNum": 1,
        "allowChangeUser": 0,
        "redirectLogin": 0,
        "urlSegments": 0,
        "https": 0,
        "slashUrls": 1,
        "slashPageNum": 0,
        "slashUrlSegments": 0,
        "altFilename": "",
        "guestSearchable": 0,
        "pageClass": "",
        "childNameFormat": "",
        "pageLabelField": "fa-calendar title",
        "noGlobal": 0,
        "noMove": 0,
        "noTrash": 0,
        "noSettings": 0,
        "noChangeTemplate": 0,
        "noShortcut": 0,
        "noUnpublish": 0,
        "noLang": 0,
        "compile": 0,
        "nameContentTab": 0,
        "noCacheGetVars": "",
        "noCachePostVars": "",
        "useCacheForUsers": 0,
        "cacheExpire": 0,
        "cacheExpirePages": [],
        "cacheExpireSelector": "",
        "label": "",
        "tags": "",
        "titleNames": 0,
        "noPrependTemplateFile": 0,
        "noAppendTemplateFile": 0,
        "prependFile": "",
        "appendFile": "",
        "pagefileSecure": 0,
        "tabContent": "",
        "tabChildren": "",
        "nameLabel": "",
        "contentType": "",
        "errorAction": 0,
        "connectedFieldID": null,
        "ns": "ProcessWire",
        "fieldgroupFields": [
            "title",
            "content"
        ],
        "fieldgroupContexts": {
            "title": [],
            "content": []
        }
    },
    "home": {
        "id": 1,
        "name": "home",
        "fieldgroups_id": "home",
        "flags": 0,
        "cache_time": 0,
        "useRoles": 1,
        "editRoles": [
            "editor",
            "admin"
        ],
        "addRoles": [
            "editor",
            "admin"
        ],
        "createRoles": [
            "editor",
            "admin"
        ],
        "rolesPermissions": [],
        "noInherit": 0,
        "childrenTemplatesID": 0,
        "sortfield": "",
        "noChildren": "",
        "noParents": 1,
        "childTemplates": [],
        "parentTemplates": [],
        "allowPageNum": 0,
        "allowChangeUser": 0,
        "redirectLogin": 0,
        "urlSegments": 0,
        "https": 0,
        "slashUrls": 1,
        "slashPageNum": 0,
        "slashUrlSegments": 0,
        "altFilename": "",
        "guestSearchable": 0,
        "pageClass": "",
        "childNameFormat": "",
        "pageLabelField": "fa-home title",
        "noGlobal": 0,
        "noMove": 0,
        "noTrash": 0,
        "noSettings": 0,
        "noChangeTemplate": 0,
        "noShortcut": 0,
        "noUnpublish": 0,
        "noLang": 0,
        "compile": 0,
        "nameContentTab": 0,
        "noCacheGetVars": "",
        "noCachePostVars": "",
        "useCacheForUsers": 0,
        "cacheExpire": 0,
        "cacheExpirePages": [],
        "cacheExpireSelector": "",
        "label": "",
        "tags": "",
        "titleNames": 0,
        "noPrependTemplateFile": 0,
        "noAppendTemplateFile": 0,
        "prependFile": "",
        "appendFile": "",
        "pagefileSecure": 0,
        "tabContent": "",
        "tabChildren": "",
        "nameLabel": "",
        "contentType": "",
        "errorAction": 0,
        "connectedFieldID": null,
        "ns": "ProcessWire",
        "roles": [
            "guest",
            "editor",
            "member",
            "admin"
        ],
        "fieldgroupFields": [
            "title",
            "content",
            "images"
        ],
        "fieldgroupContexts": {
            "title": [],
            "content": [],
            "images": []
        }
    },
    "inventory": {
        "id": 56,
        "name": "inventory",
        "fieldgroups_id": "inventory",
        "flags": 0,
        "cache_time": 0,
        "useRoles": 0,
        "noInherit": 0,
        "childrenTemplatesID": 0,
        "sortfield": "",
        "noChildren": "",
        "noParents": -1,
        "childTemplates": [
            "inventory-item"
        ],
        "parentTemplates": [],
        "allowPageNum": 0,
        "allowChangeUser": 0,
        "redirectLogin": 0,
        "urlSegments": 0,
        "https": 0,
        "slashUrls": 1,
        "slashPageNum": 0,
        "slashUrlSegments": 0,
        "altFilename": "",
        "guestSearchable": 0,
        "pageClass": "",
        "childNameFormat": "",
        "pageLabelField": "fa-cogs title",
        "noGlobal": 0,
        "noMove": 0,
        "noTrash": 0,
        "noSettings": 0,
        "noChangeTemplate": 0,
        "noShortcut": 0,
        "noUnpublish": 0,
        "noLang": 0,
        "compile": 0,
        "nameContentTab": 0,
        "noCacheGetVars": "",
        "noCachePostVars": "",
        "useCacheForUsers": 0,
        "cacheExpire": 0,
        "cacheExpirePages": [],
        "cacheExpireSelector": "",
        "label": "",
        "tags": "",
        "titleNames": 0,
        "noPrependTemplateFile": 0,
        "noAppendTemplateFile": 0,
        "prependFile": "",
        "appendFile": "",
        "pagefileSecure": 0,
        "tabContent": "",
        "tabChildren": "",
        "nameLabel": "",
        "contentType": "",
        "errorAction": 0,
        "connectedFieldID": null,
        "ns": "ProcessWire",
        "fieldgroupFields": [
            "title",
            "content"
        ],
        "fieldgroupContexts": {
            "title": [],
            "content": []
        }
    },
    "inventory-item": {
        "id": 55,
        "name": "inventory-item",
        "fieldgroups_id": "inventory-item",
        "flags": 0,
        "cache_time": 0,
        "useRoles": 0,
        "noInherit": 0,
        "childrenTemplatesID": 0,
        "sortfield": "",
        "noChildren": "",
        "noParents": "",
        "childTemplates": [],
        "parentTemplates": [
            "inventory"
        ],
        "allowPageNum": 0,
        "allowChangeUser": 0,
        "redirectLogin": 0,
        "urlSegments": 0,
        "https": 0,
        "slashUrls": 1,
        "slashPageNum": 0,
        "slashUrlSegments": 0,
        "altFilename": "",
        "guestSearchable": 0,
        "pageClass": "",
        "childNameFormat": "",
        "pageLabelField": "fa-cog title",
        "noGlobal": 0,
        "noMove": 0,
        "noTrash": 0,
        "noSettings": 0,
        "noChangeTemplate": 0,
        "noShortcut": 0,
        "noUnpublish": 0,
        "noLang": 0,
        "compile": 0,
        "nameContentTab": 0,
        "noCacheGetVars": "",
        "noCachePostVars": "",
        "useCacheForUsers": 0,
        "cacheExpire": 0,
        "cacheExpirePages": [],
        "cacheExpireSelector": "",
        "label": "Inventory Item",
        "tags": "",
        "titleNames": 0,
        "noPrependTemplateFile": 0,
        "noAppendTemplateFile": 0,
        "prependFile": "",
        "appendFile": "",
        "pagefileSecure": 0,
        "tabContent": "",
        "tabChildren": "",
        "nameLabel": "",
        "contentType": "",
        "errorAction": 0,
        "connectedFieldID": null,
        "ns": "ProcessWire",
        "label1021": "Inventory Item",
        "fieldgroupFields": [
            "title"
        ],
        "fieldgroupContexts": {
            "title": []
        }
    },
    "language": {
        "id": 44,
        "name": "language",
        "fieldgroups_id": "language",
        "flags": 8,
        "cache_time": 0,
        "useRoles": 0,
        "noInherit": 0,
        "childrenTemplatesID": 0,
        "sortfield": "",
        "noChildren": "",
        "noParents": "",
        "childTemplates": [],
        "parentTemplates": [
            "admin"
        ],
        "allowPageNum": 0,
        "allowChangeUser": 0,
        "redirectLogin": 0,
        "urlSegments": 0,
        "https": 0,
        "slashUrls": 1,
        "slashPageNum": 0,
        "slashUrlSegments": 0,
        "altFilename": "",
        "guestSearchable": 0,
        "pageClass": "Language",
        "childNameFormat": "",
        "pageLabelField": "name",
        "noGlobal": 1,
        "noMove": 1,
        "noTrash": 1,
        "noSettings": 0,
        "noChangeTemplate": 1,
        "noShortcut": 0,
        "noUnpublish": 1,
        "noLang": 0,
        "compile": 3,
        "nameContentTab": 1,
        "noCacheGetVars": "",
        "noCachePostVars": "",
        "useCacheForUsers": 0,
        "cacheExpire": 0,
        "cacheExpirePages": [],
        "cacheExpireSelector": "",
        "label": "",
        "tags": "",
        "titleNames": 0,
        "noPrependTemplateFile": 0,
        "noAppendTemplateFile": 0,
        "prependFile": "",
        "appendFile": "",
        "pagefileSecure": 0,
        "tabContent": "",
        "tabChildren": "",
        "nameLabel": "",
        "contentType": "",
        "errorAction": 0,
        "connectedFieldID": null,
        "ns": "",
        "fieldgroupFields": [
            "title",
            "language_files_site",
            "language_files"
        ],
        "fieldgroupContexts": {
            "title": [],
            "language_files_site": [],
            "language_files": []
        }
    },
    "member": {
        "id": 49,
        "name": "member",
        "fieldgroups_id": "member",
        "flags": 0,
        "cache_time": 0,
        "useRoles": 0,
        "noInherit": 0,
        "childrenTemplatesID": 0,
        "sortfield": "",
        "noChildren": "",
        "noParents": "",
        "childTemplates": [],
        "parentTemplates": [],
        "allowPageNum": 0,
        "allowChangeUser": 0,
        "redirectLogin": 0,
        "urlSegments": 0,
        "https": 0,
        "slashUrls": 1,
        "slashPageNum": 0,
        "slashUrlSegments": 0,
        "altFilename": "",
        "guestSearchable": 0,
        "pageClass": "",
        "childNameFormat": "",
        "pageLabelField": "fa-user title",
        "noGlobal": 0,
        "noMove": 0,
        "noTrash": 0,
        "noSettings": 0,
        "noChangeTemplate": 0,
        "noShortcut": 0,
        "noUnpublish": 0,
        "noLang": 0,
        "compile": 0,
        "nameContentTab": 0,
        "noCacheGetVars": "",
        "noCachePostVars": "",
        "useCacheForUsers": 0,
        "cacheExpire": 0,
        "cacheExpirePages": [],
        "cacheExpireSelector": "",
        "label": "",
        "tags": "",
        "titleNames": 0,
        "noPrependTemplateFile": 0,
        "noAppendTemplateFile": 0,
        "prependFile": "",
        "appendFile": "",
        "pagefileSecure": 0,
        "tabContent": "",
        "tabChildren": "",
        "nameLabel": "",
        "contentType": "",
        "errorAction": 0,
        "connectedFieldID": null,
        "ns": "\\",
        "fieldgroupFields": [
            "title"
        ],
        "fieldgroupContexts": {
            "title": []
        }
    },
    "members-overview": {
        "id": 50,
        "name": "members-overview",
        "fieldgroups_id": "members-overview",
        "flags": 0,
        "cache_time": 0,
        "useRoles": 0,
        "noInherit": 0,
        "childrenTemplatesID": 0,
        "sortfield": "",
        "noChildren": 1,
        "noParents": -1,
        "childTemplates": [],
        "parentTemplates": [],
        "allowPageNum": 0,
        "allowChangeUser": 0,
        "redirectLogin": 0,
        "urlSegments": 1,
        "https": 0,
        "slashUrls": 1,
        "slashPageNum": 0,
        "slashUrlSegments": 0,
        "altFilename": "",
        "guestSearchable": 0,
        "pageClass": "",
        "childNameFormat": "",
        "pageLabelField": "fa-users title",
        "noGlobal": 0,
        "noMove": 0,
        "noTrash": 0,
        "noSettings": 0,
        "noChangeTemplate": 0,
        "noShortcut": 0,
        "noUnpublish": 0,
        "noLang": 0,
        "compile": 0,
        "nameContentTab": 0,
        "noCacheGetVars": "",
        "noCachePostVars": "",
        "useCacheForUsers": 0,
        "cacheExpire": 0,
        "cacheExpirePages": [],
        "cacheExpireSelector": "",
        "label": "Users",
        "tags": "",
        "titleNames": 0,
        "noPrependTemplateFile": 0,
        "noAppendTemplateFile": 0,
        "prependFile": "",
        "appendFile": "",
        "pagefileSecure": 0,
        "tabContent": "",
        "tabChildren": "",
        "nameLabel": "",
        "contentType": "",
        "errorAction": 0,
        "connectedFieldID": null,
        "ns": "ProcessWire",
        "label1021": "Users",
        "fieldgroupFields": [
            "title",
            "content"
        ],
        "fieldgroupContexts": {
            "title": [],
            "content": []
        }
    },
    "menus": {
        "id": 46,
        "name": "menus",
        "fieldgroups_id": "menus",
        "flags": 0,
        "cache_time": 0,
        "useRoles": 0,
        "noInherit": 0,
        "childrenTemplatesID": 0,
        "sortfield": "",
        "noChildren": 1,
        "noParents": "",
        "childTemplates": [],
        "parentTemplates": [
            "admin"
        ],
        "allowPageNum": 0,
        "allowChangeUser": 0,
        "redirectLogin": 0,
        "urlSegments": 0,
        "https": 0,
        "slashUrls": 1,
        "slashPageNum": 0,
        "slashUrlSegments": 0,
        "altFilename": "",
        "guestSearchable": 0,
        "pageClass": "",
        "childNameFormat": "",
        "pageLabelField": "fa-list title",
        "noGlobal": 0,
        "noMove": 0,
        "noTrash": 0,
        "noSettings": 0,
        "noChangeTemplate": 0,
        "noShortcut": 0,
        "noUnpublish": 0,
        "noLang": 0,
        "compile": 0,
        "nameContentTab": 0,
        "noCacheGetVars": "",
        "noCachePostVars": "",
        "useCacheForUsers": 0,
        "cacheExpire": 0,
        "cacheExpirePages": [],
        "cacheExpireSelector": "",
        "label": "Menus",
        "tags": "menu",
        "titleNames": 0,
        "noPrependTemplateFile": 0,
        "noAppendTemplateFile": 0,
        "prependFile": "",
        "appendFile": "",
        "pagefileSecure": 0,
        "tabContent": "",
        "tabChildren": "",
        "nameLabel": "",
        "contentType": "",
        "errorAction": 0,
        "connectedFieldID": null,
        "ns": "",
        "label1021": "Menues",
        "fieldgroupFields": [
            "title",
            "menu_pages",
            "menu_items",
            "menu_settings"
        ],
        "fieldgroupContexts": {
            "title": [],
            "menu_pages": [],
            "menu_items": [],
            "menu_settings": []
        }
    },
    "news": {
        "id": 57,
        "name": "news",
        "fieldgroups_id": "news",
        "flags": 0,
        "cache_time": 0,
        "useRoles": 0,
        "noInherit": 0,
        "childrenTemplatesID": 0,
        "sortfield": "",
        "noChildren": 1,
        "noParents": "",
        "childTemplates": [],
        "parentTemplates": [
            "news-overview"
        ],
        "allowPageNum": 0,
        "allowChangeUser": 0,
        "redirectLogin": 0,
        "urlSegments": 0,
        "https": 0,
        "slashUrls": 1,
        "slashPageNum": 0,
        "slashUrlSegments": 0,
        "altFilename": "",
        "guestSearchable": 0,
        "pageClass": "",
        "childNameFormat": "",
        "pageLabelField": "fa-newspaper-o title",
        "noGlobal": 0,
        "noMove": 0,
        "noTrash": 0,
        "noSettings": 0,
        "noChangeTemplate": 0,
        "noShortcut": 0,
        "noUnpublish": 0,
        "noLang": 0,
        "compile": 0,
        "nameContentTab": 0,
        "noCacheGetVars": "",
        "noCachePostVars": "",
        "useCacheForUsers": 0,
        "cacheExpire": 0,
        "cacheExpirePages": [],
        "cacheExpireSelector": "",
        "label": "News",
        "tags": "",
        "titleNames": 0,
        "noPrependTemplateFile": 0,
        "noAppendTemplateFile": 0,
        "prependFile": "",
        "appendFile": "",
        "pagefileSecure": 0,
        "tabContent": "",
        "tabChildren": "",
        "nameLabel": "",
        "contentType": "",
        "errorAction": 0,
        "connectedFieldID": null,
        "ns": "ProcessWire",
        "label1021": "News",
        "fieldgroupFields": [
            "title",
            "date",
            "abstract",
            "content",
            "images",
            "reference"
        ],
        "fieldgroupContexts": {
            "title": {
                "columnWidth": 50
            },
            "date": {
                "columnWidth": 50
            },
            "abstract": [],
            "content": [],
            "images": {
                "columnWidth": 50
            },
            "reference": {
                "columnWidth": 50
            }
        }
    },
    "news-overview": {
        "id": 58,
        "name": "news-overview",
        "fieldgroups_id": "news-overview",
        "flags": 0,
        "cache_time": 0,
        "useRoles": 0,
        "noInherit": 0,
        "childrenTemplatesID": 0,
        "sortfield": "",
        "noChildren": "",
        "noParents": -1,
        "childTemplates": [
            "news"
        ],
        "parentTemplates": [],
        "allowPageNum": 0,
        "allowChangeUser": 0,
        "redirectLogin": 0,
        "urlSegments": 0,
        "https": 0,
        "slashUrls": 1,
        "slashPageNum": 0,
        "slashUrlSegments": 0,
        "altFilename": "",
        "guestSearchable": 0,
        "pageClass": "",
        "childNameFormat": "",
        "pageLabelField": "fa-newspaper-o title",
        "noGlobal": 0,
        "noMove": 0,
        "noTrash": 0,
        "noSettings": 0,
        "noChangeTemplate": 0,
        "noShortcut": 0,
        "noUnpublish": 0,
        "noLang": 0,
        "compile": 0,
        "nameContentTab": 0,
        "noCacheGetVars": "",
        "noCachePostVars": "",
        "useCacheForUsers": 0,
        "cacheExpire": 0,
        "cacheExpirePages": [],
        "cacheExpireSelector": "",
        "label": "News Overview",
        "tags": "",
        "titleNames": 0,
        "noPrependTemplateFile": 0,
        "noAppendTemplateFile": 0,
        "prependFile": "",
        "appendFile": "",
        "pagefileSecure": 0,
        "tabContent": "",
        "tabChildren": "",
        "nameLabel": "",
        "contentType": "",
        "errorAction": 0,
        "connectedFieldID": null,
        "ns": "ProcessWire",
        "label1021": "News Overview",
        "fieldgroupFields": [
            "title"
        ],
        "fieldgroupContexts": {
            "title": []
        }
    },
    "permission": {
        "id": 5,
        "name": "permission",
        "fieldgroups_id": "permission",
        "flags": 8,
        "cache_time": 0,
        "useRoles": 0,
        "noInherit": 0,
        "childrenTemplatesID": 0,
        "sortfield": "",
        "noChildren": 1,
        "noParents": "",
        "childTemplates": [],
        "parentTemplates": [
            "admin"
        ],
        "allowPageNum": 0,
        "allowChangeUser": 0,
        "redirectLogin": 0,
        "urlSegments": 0,
        "https": 0,
        "slashUrls": 1,
        "slashPageNum": 0,
        "slashUrlSegments": 0,
        "altFilename": "",
        "guestSearchable": 1,
        "pageClass": "Permission",
        "childNameFormat": "",
        "pageLabelField": "",
        "noGlobal": 1,
        "noMove": 1,
        "noTrash": 1,
        "noSettings": 1,
        "noChangeTemplate": 1,
        "noShortcut": 0,
        "noUnpublish": 0,
        "noLang": 0,
        "compile": 3,
        "nameContentTab": 1,
        "noCacheGetVars": "",
        "noCachePostVars": "",
        "useCacheForUsers": 0,
        "cacheExpire": 0,
        "cacheExpirePages": [],
        "cacheExpireSelector": "",
        "label": "",
        "tags": "",
        "titleNames": 0,
        "noPrependTemplateFile": 0,
        "noAppendTemplateFile": 0,
        "prependFile": "",
        "appendFile": "",
        "pagefileSecure": 0,
        "tabContent": "",
        "tabChildren": "",
        "nameLabel": "",
        "contentType": "",
        "errorAction": 0,
        "connectedFieldID": null,
        "ns": "",
        "fieldgroupFields": [
            "title"
        ],
        "fieldgroupContexts": {
            "title": []
        }
    },
    "post": {
        "id": 51,
        "name": "post",
        "fieldgroups_id": "post",
        "flags": 0,
        "cache_time": 0,
        "useRoles": 0,
        "noInherit": 0,
        "childrenTemplatesID": 0,
        "sortfield": "",
        "noChildren": "",
        "noParents": "",
        "childTemplates": [],
        "parentTemplates": [],
        "allowPageNum": 0,
        "allowChangeUser": 0,
        "redirectLogin": 0,
        "urlSegments": 0,
        "https": 0,
        "slashUrls": 1,
        "slashPageNum": 0,
        "slashUrlSegments": 0,
        "altFilename": "",
        "guestSearchable": 0,
        "pageClass": "",
        "childNameFormat": "",
        "pageLabelField": "fa-pencil title",
        "noGlobal": 0,
        "noMove": 0,
        "noTrash": 0,
        "noSettings": 0,
        "noChangeTemplate": 0,
        "noShortcut": 0,
        "noUnpublish": 0,
        "noLang": 0,
        "compile": 0,
        "nameContentTab": 0,
        "noCacheGetVars": "",
        "noCachePostVars": "",
        "useCacheForUsers": 0,
        "cacheExpire": 0,
        "cacheExpirePages": [],
        "cacheExpireSelector": "",
        "label": "Post",
        "tags": "",
        "titleNames": 0,
        "noPrependTemplateFile": 0,
        "noAppendTemplateFile": 0,
        "prependFile": "",
        "appendFile": "",
        "pagefileSecure": 0,
        "tabContent": "",
        "tabChildren": "",
        "nameLabel": "",
        "contentType": "",
        "errorAction": 0,
        "connectedFieldID": null,
        "ns": "ProcessWire",
        "label1026": "Post",
        "fieldgroupFields": [
            "title",
            "content",
            "images",
            "event_reference"
        ],
        "fieldgroupContexts": {
            "title": [],
            "content": [],
            "images": [],
            "event_reference": []
        }
    },
    "project": {
        "id": 53,
        "name": "project",
        "fieldgroups_id": "project",
        "flags": 0,
        "cache_time": 0,
        "useRoles": 0,
        "noInherit": 0,
        "childrenTemplatesID": 0,
        "sortfield": "",
        "noChildren": "",
        "noParents": "",
        "childTemplates": [
            "basic-page",
            "project-subpage"
        ],
        "parentTemplates": [],
        "allowPageNum": 0,
        "allowChangeUser": 0,
        "redirectLogin": 0,
        "urlSegments": 0,
        "https": 0,
        "slashUrls": 1,
        "slashPageNum": 0,
        "slashUrlSegments": 0,
        "altFilename": "",
        "guestSearchable": 0,
        "pageClass": "",
        "childNameFormat": "",
        "pageLabelField": "fa-product-hunt title",
        "noGlobal": 0,
        "noMove": 0,
        "noTrash": 0,
        "noSettings": 0,
        "noChangeTemplate": 0,
        "noShortcut": 0,
        "noUnpublish": 0,
        "noLang": 0,
        "compile": 0,
        "nameContentTab": 0,
        "noCacheGetVars": "",
        "noCachePostVars": "",
        "useCacheForUsers": 0,
        "cacheExpire": 0,
        "cacheExpirePages": [],
        "cacheExpireSelector": "",
        "label": "Project",
        "tags": "",
        "titleNames": 0,
        "noPrependTemplateFile": 0,
        "noAppendTemplateFile": 0,
        "prependFile": "",
        "appendFile": "",
        "pagefileSecure": 0,
        "tabContent": "",
        "tabChildren": "",
        "nameLabel": "",
        "contentType": "",
        "errorAction": 0,
        "connectedFieldID": null,
        "ns": "ProcessWire",
        "label1021": "Project",
        "fieldgroupFields": [
            "title",
            "content",
            "images",
            "user_reference"
        ],
        "fieldgroupContexts": {
            "title": [],
            "content": [],
            "images": [],
            "user_reference": []
        }
    },
    "project-subpage": {
        "id": 59,
        "name": "project-subpage",
        "fieldgroups_id": "project-subpage",
        "flags": 0,
        "cache_time": 0,
        "useRoles": 0,
        "noInherit": 0,
        "childrenTemplatesID": 0,
        "sortfield": "",
        "noChildren": "",
        "noParents": "",
        "childTemplates": [
            "basic-page",
            "project-subpage"
        ],
        "parentTemplates": [
            "basic-page",
            "project-subpage",
            "project"
        ],
        "allowPageNum": 0,
        "allowChangeUser": 0,
        "redirectLogin": 0,
        "urlSegments": 0,
        "https": 0,
        "slashUrls": 1,
        "slashPageNum": 0,
        "slashUrlSegments": 0,
        "altFilename": "",
        "guestSearchable": 0,
        "pageClass": "",
        "childNameFormat": "",
        "pageLabelField": "fa-product-hunt title",
        "noGlobal": 0,
        "noMove": 0,
        "noTrash": 0,
        "noSettings": 0,
        "noChangeTemplate": 0,
        "noShortcut": 0,
        "noUnpublish": 0,
        "noLang": 0,
        "compile": 0,
        "nameContentTab": 0,
        "noCacheGetVars": "",
        "noCachePostVars": "",
        "useCacheForUsers": 0,
        "cacheExpire": 0,
        "cacheExpirePages": [],
        "cacheExpireSelector": "",
        "label": "Project Subpage",
        "tags": "",
        "titleNames": 0,
        "noPrependTemplateFile": 0,
        "noAppendTemplateFile": 0,
        "prependFile": "",
        "appendFile": "",
        "pagefileSecure": 0,
        "tabContent": "",
        "tabChildren": "",
        "nameLabel": "",
        "contentType": "",
        "errorAction": 0,
        "connectedFieldID": null,
        "ns": "ProcessWire",
        "label1021": "Project Subpage",
        "fieldgroupFields": [
            "title",
            "content",
            "images"
        ],
        "fieldgroupContexts": {
            "title": [],
            "content": [],
            "images": []
        }
    },
    "projects-overview": {
        "id": 52,
        "name": "projects-overview",
        "fieldgroups_id": "projects-overview",
        "flags": 0,
        "cache_time": 0,
        "useRoles": 1,
        "editRoles": [
            "editor",
            "admin"
        ],
        "addRoles": [
            "editor",
            "admin"
        ],
        "createRoles": [
            "admin"
        ],
        "rolesPermissions": [],
        "noInherit": 0,
        "childrenTemplatesID": 0,
        "sortfield": "",
        "noChildren": "",
        "noParents": -1,
        "childTemplates": [
            "project"
        ],
        "parentTemplates": [],
        "allowPageNum": 0,
        "allowChangeUser": 0,
        "redirectLogin": 0,
        "urlSegments": 0,
        "https": 0,
        "slashUrls": 1,
        "slashPageNum": 0,
        "slashUrlSegments": 0,
        "altFilename": "",
        "guestSearchable": 0,
        "pageClass": "",
        "childNameFormat": "",
        "pageLabelField": "fa-product-hunt title",
        "noGlobal": 0,
        "noMove": 0,
        "noTrash": 0,
        "noSettings": 0,
        "noChangeTemplate": 0,
        "noShortcut": 0,
        "noUnpublish": 0,
        "noLang": 0,
        "compile": 0,
        "nameContentTab": 0,
        "noCacheGetVars": "",
        "noCachePostVars": "",
        "useCacheForUsers": 0,
        "cacheExpire": 0,
        "cacheExpirePages": [],
        "cacheExpireSelector": "",
        "label": "Projects Overview",
        "tags": "",
        "titleNames": 0,
        "noPrependTemplateFile": 0,
        "noAppendTemplateFile": 0,
        "prependFile": "",
        "appendFile": "",
        "pagefileSecure": 0,
        "tabContent": "",
        "tabChildren": "",
        "nameLabel": "",
        "contentType": "",
        "errorAction": 0,
        "connectedFieldID": null,
        "ns": "ProcessWire",
        "label1021": "Projects Overview",
        "roles": [
            "guest",
            "editor",
            "member",
            "admin"
        ],
        "fieldgroupFields": [
            "title",
            "content"
        ],
        "fieldgroupContexts": {
            "title": [],
            "content": []
        }
    },
    "role": {
        "id": 4,
        "name": "role",
        "fieldgroups_id": "role",
        "flags": 8,
        "cache_time": 0,
        "useRoles": 0,
        "noInherit": 0,
        "childrenTemplatesID": 0,
        "sortfield": "",
        "noChildren": 1,
        "noParents": "",
        "childTemplates": [],
        "parentTemplates": [
            "admin"
        ],
        "allowPageNum": 0,
        "allowChangeUser": 0,
        "redirectLogin": 0,
        "urlSegments": 0,
        "https": 0,
        "slashUrls": 1,
        "slashPageNum": 0,
        "slashUrlSegments": 0,
        "altFilename": "",
        "guestSearchable": 0,
        "pageClass": "Role",
        "childNameFormat": "",
        "pageLabelField": "",
        "noGlobal": 1,
        "noMove": 1,
        "noTrash": 1,
        "noSettings": 1,
        "noChangeTemplate": 1,
        "noShortcut": 0,
        "noUnpublish": 0,
        "noLang": 0,
        "compile": 3,
        "nameContentTab": 1,
        "noCacheGetVars": "",
        "noCachePostVars": "",
        "useCacheForUsers": 0,
        "cacheExpire": 0,
        "cacheExpirePages": [],
        "cacheExpireSelector": "",
        "label": "",
        "tags": "",
        "titleNames": 0,
        "noPrependTemplateFile": 0,
        "noAppendTemplateFile": 0,
        "prependFile": "",
        "appendFile": "",
        "pagefileSecure": 0,
        "tabContent": "",
        "tabChildren": "",
        "nameLabel": "",
        "contentType": "",
        "errorAction": 0,
        "connectedFieldID": null,
        "ns": "",
        "fieldgroupFields": [
            "permissions"
        ],
        "fieldgroupContexts": {
            "permissions": []
        }
    },
    "user": {
        "id": 3,
        "name": "user",
        "fieldgroups_id": "user",
        "flags": 8,
        "cache_time": 0,
        "useRoles": 1,
        "editRoles": [],
        "addRoles": [],
        "createRoles": [],
        "rolesPermissions": [],
        "noInherit": 0,
        "childrenTemplatesID": 0,
        "sortfield": "",
        "noChildren": 1,
        "noParents": "",
        "childTemplates": [],
        "parentTemplates": [
            "admin"
        ],
        "allowPageNum": 0,
        "allowChangeUser": 0,
        "redirectLogin": 0,
        "urlSegments": 0,
        "https": 0,
        "slashUrls": 1,
        "slashPageNum": 0,
        "slashUrlSegments": 0,
        "altFilename": "",
        "guestSearchable": 0,
        "pageClass": "User",
        "childNameFormat": "",
        "pageLabelField": "",
        "noGlobal": 1,
        "noMove": 1,
        "noTrash": 1,
        "noSettings": 1,
        "noChangeTemplate": 1,
        "noShortcut": 0,
        "noUnpublish": 0,
        "noLang": 0,
        "compile": 0,
        "nameContentTab": 1,
        "noCacheGetVars": "",
        "noCachePostVars": "",
        "useCacheForUsers": 0,
        "cacheExpire": 0,
        "cacheExpirePages": [],
        "cacheExpireSelector": "",
        "label": "",
        "tags": "",
        "titleNames": 0,
        "noPrependTemplateFile": 0,
        "noAppendTemplateFile": 0,
        "prependFile": "",
        "appendFile": "",
        "pagefileSecure": 0,
        "tabContent": "",
        "tabChildren": "",
        "nameLabel": "",
        "contentType": "",
        "errorAction": 0,
        "connectedFieldID": null,
        "ns": "",
        "roles": [],
        "fieldgroupFields": [
            "pass",
            "email",
            "roles",
            "admin_theme",
            "language",
            "user_display_name",
            "content",
            "images",
            "user_nice_url",
            "user_byline",
            "color"
        ],
        "fieldgroupContexts": {
            "pass": [],
            "email": [],
            "roles": [],
            "admin_theme": [],
            "language": [],
            "user_display_name": [],
            "content": [],
            "images": [],
            "user_nice_url": {
                "columnWidth": 33
            },
            "user_byline": {
                "columnWidth": 33
            },
            "color": {
                "columnWidth": 34
            }
        }
    }
}
